crdts/__init__.py
crdts/causaltree.py
crdts/classes.py
crdts/counter.py
crdts/counterset.py
crdts/datawrappers.py
crdts/document.py
crdts/errors.py
crdts/fiarray.py
crdts/gset.py
crdts/interfaces.py
crdts/lwwmap.py
crdts/lwwregister.py
crdts/merkle.py
crdts/mvmap.py
crdts/mvregister.py
crdts/orset.py
crdts/pncounter.py
crdts/rgarray.py
crdts/scalarclock.py
crdts/stateupdate.py
crdts-0.0.4.dist-info/METADATA
crdts-0.0.4.dist-info/WHEEL
crdts-0.0.4.dist-info/RECORD
