Metadata-Version: 2.1
Name: crdts
Version: 0.0.4
Summary: A library of Conflict-free Replicated Data Types (12 included)
Project-URL: Homepage, https://github.com/k98kurz/CRDTs
Project-URL: Bug Tracker, https://github.com/k98kurz/CRDTs/issues
Author-email: k98kurz <k98kurz@gmail.com>
Classifier: Development Status :: 3 - Alpha
Classifier: License :: OSI Approved :: ISC License (ISCL)
Classifier: Operating System :: OS Independent
Classifier: Programming Language :: Python :: 3
Classifier: Topic :: Other/Nonlisted Topic
Classifier: Topic :: Scientific/Engineering :: Mathematics
Requires-Python: >=3.10
Requires-Dist: packify>=0.2.2
